geforce_temp_monitor/__init__.py
geforce_temp_monitor/monitor.py
GeforceTempMonitor-0.2.0.dist-info/LICENSE
GeforceTempMonitor-0.2.0.dist-info/METADATA
GeforceTempMonitor-0.2.0.dist-info/WHEEL
GeforceTempMonitor-0.2.0.dist-info/entry_points.txt
GeforceTempMonitor-0.2.0.dist-info/top_level.txt
GeforceTempMonitor-0.2.0.dist-info/RECORD
