Metadata-Version: 2.1
Name: GeforceTempMonitor
Version: 0.2.0
Summary: A Python library to monitor temperatures for GeForce cards using nvidia-smi.
Author: Ryan K
License: MIT
License-File: LICENSE
